efts_io-0.7.0.dist-info/METADATA
efts_io-0.7.0.dist-info/WHEEL
efts_io-0.7.0.dist-info/entry_points.txt
efts_io-0.7.0.dist-info/licenses/LICENSE
efts_io/.ruff_cache/.gitignore
efts_io/.ruff_cache/0.5.7/18310219444739732399
efts_io/.ruff_cache/CACHEDIR.TAG
efts_io/__init__.py
efts_io/__main__.py
efts_io/_internals.py
efts_io/_ncdf_stf2.py
efts_io/attributes.py
efts_io/cli.py
efts_io/conventions.py
efts_io/data/bak.nc
efts_io/data/derived_rainfall_tas.nc
efts_io/debug.py
efts_io/dimensions.py
efts_io/helpers.py
efts_io/py.typed
efts_io/variables.py
efts_io/wrapper.py
efts_io-0.7.0.dist-info/RECORD
