Metadata-Version: 2.1
Name: efts-io
Version: 0.7.0
Summary: Ensemble forecast time series
Author-Email: J-M <jean-michel.perraud@csiro.au>
License: BSD-3-Clause-Clear
Classifier: Development Status :: 4 - Beta
Classifier: Intended Audience :: Developers
Classifier: Programming Language :: Python
Classifier: Programming Language :: Python :: 3
Classifier: Programming Language :: Python :: 3 :: Only
Classifier: Programming Language :: Python :: 3.10
Classifier: Programming Language :: Python :: 3.11
Classifier: Programming Language :: Python :: 3.12
Classifier: Programming Language :: Python :: 3.13
Classifier: Topic :: Documentation
Classifier: Topic :: Software Development
Classifier: Topic :: Utilities
Classifier: Typing :: Typed
Project-URL: Homepage, https://csiro-hydroinformatics.github.io/efts-io
Project-URL: Documentation, https://csiro-hydroinformatics.github.io/efts-io
Project-URL: Changelog, https://csiro-hydroinformatics.github.io/efts-io/changelog
Project-URL: Repository, https://github.com/csiro-hydroinformatics/efts-io
Project-URL: Issues, https://github.com/csiro-hydroinformatics/efts-io/issues
Project-URL: Discussions, https://github.com/csiro-hydroinformatics/efts-io/discussions
Requires-Python: >=3.10
Requires-Dist: pandas
Requires-Dist: numpy
Requires-Dist: xarray
Requires-Dist: cf-xarray
Requires-Dist: pint-xarray
Requires-Dist: cftime
Requires-Dist: netcdf4>=1.7.1.post2
